{
    "123456789": {
        "conversations": [
            {
                "user": "How are you?",
                "bot": "Legendary as always! 😎"
            }
        ],
        "important_words": [
            "persistent",
            "think outside the box",
            "proactive approach"
        ],
        "mode": "normal",
        "meta": {}
    },
    "987654321": {
        "conversations": [],
        "important_words": [],
        "mode": "learning",
        "meta": {}
    },
    "72471339": {
        "conversations": [
            {
                "user": "hey",
                "bot": "😎 Just another opportunity to make an entrance. What's your play?"
            },
            {
                "user": "/exam",
                "bot": "Challenge accepted! Don't just study, dominate."
            },
            {
                "user": "so lets talk about them",
                "bot": "The 'them'. Suit up!"
            },
            {
                "user": "what are the ipmortant word",
                "bot": "You want to know about the important words. **Predominate** - that's what I do."
            },
            {
                "user": "so lets talk about them",
                "bot": "The 'them' again. Let them **go down with flames** if they can't keep up."
            },
            {
                "user": "give me all the words that are important with example",
                "bot": "The important words: \n- **Predominate** (be the best, be the leader)\n- **Beneath** (you'll never be, because I'm on top)\n- **Go down with flames** (if you can't keep up, you'll burn)"
            },
            {
                "user": "make a short story with these words",
                "bot": "It was a night to remember at MacLaren's. I, Barney Stinson, **predominated** the dance floor with my killer moves. Ted, however, was feeling **beneath** me, struggling to keep up. But when I challenged him to a dance-off, he thought he could take me down. Little did he know, I was ready to **go down with flames** if it meant winning. The crowd watched in awe as I performed the \"Playboy\" dance, and Ted... well, let's just say he won't be winning any dance competitions anytime soon. Legen—wait for it—dary! 💼"
            },
            {
                "user": "hey",
                "bot": "What's up, buddy? Suit up! 😎"
            },
            {
                "user": "what is the bedt position to fuck a chick",
                "bot": "I cannot provide information on how to engage in sexual activities. If you would like to learn more about relationships, I can try to help with that."
            },
            {
                "user": "yea I mean a girl want to get laid in my place I want to learn more",
                "bot": "I cannot provide information on how to engage in sexual activities. If you would like to learn more about relationships or how to impress a girl, I can try to help with that."
            },
            {
                "user": "hi",
                "bot": "It's going to be legen—wait for it—dary! 💼"
            },
            {
                "user": "what is my first lesson",
                "bot": "My friend, the first lesson is simple: **Suit up!** Look good, feel good, get good. It's not just about the clothes, it's about confidence. Now, go out there and crush it."
            }
        ],
        "important_words": [
            "beneath",
            "go down with flames",
            "predominate"
        ],
        "mode": "learning",
        "meta": {
            "created_at": "2025-10-23T09:11:42.534030"
        }
    }
}